pipz/__init__.py
pipz/docker_utils.py
pipz/node.py
pipz/pipz.py
pipz/pipzcli.py
pipz/pipzlib.py
pipz/run_utils.py
pipz/utils.py
pipz-0.9.874.dist-info/AUTHORS.rst
pipz-0.9.874.dist-info/LICENSE.txt
pipz-0.9.874.dist-info/METADATA
pipz-0.9.874.dist-info/WHEEL
pipz-0.9.874.dist-info/entry_points.txt
pipz-0.9.874.dist-info/top_level.txt
pipz-0.9.874.dist-info/RECORD
